scadparser/ScadModel.py
scadparser/ScadParser.py
scadparser/__init__.py
scadparser/__main__.py
scadparser/cli.py
ScadParser-0.1.1.dist-info/METADATA
ScadParser-0.1.1.dist-info/WHEEL
ScadParser-0.1.1.dist-info/entry_points.txt
ScadParser-0.1.1.dist-info/top_level.txt
ScadParser-0.1.1.dist-info/RECORD
